ipynb_py_convert/__init__.py
ipynb_py_convert/__main__.py
py2ipynb-0.0.6.dist-info/LICENSE
py2ipynb-0.0.6.dist-info/METADATA
py2ipynb-0.0.6.dist-info/WHEEL
py2ipynb-0.0.6.dist-info/entry_points.txt
py2ipynb-0.0.6.dist-info/top_level.txt
py2ipynb-0.0.6.dist-info/RECORD
