Metadata-Version: 2.1
Name: py2ipynb
Version: 0.0.6
Summary: Convert .py files runnable in VSCode/Python or Atom/Hydrogen to jupyter .ipynb notebooks and vice versa
Home-page: UNKNOWN
Author: Tae Hwan Jung
Author-email: graykode@gmail.com
License: MIT
Keywords: vscode,jupyter,convert,ipynb,py,atom,hydrogen
Platform: UNKNOWN
